devdock/__init__.py
devdock/cli.py
devdock/config/__init__.py
devdock/config/config_manager.py
devdock/manager.py
devdock/shell.py
devdock-0.1.0.dist-info/LICENSE
devdock-0.1.0.dist-info/METADATA
devdock-0.1.0.dist-info/WHEEL
devdock-0.1.0.dist-info/entry_points.txt
devdock-0.1.0.dist-info/RECORD
